pyworldquant/__version__.py
pyworldquant/api.py
pyworldquant/lib/utils.py
pyworldquant/spot/__init__.py
pyworldquant/spot/_simulate.py
pyworldquant-0.0.2.dist-info/LICENSE
pyworldquant-0.0.2.dist-info/METADATA
pyworldquant-0.0.2.dist-info/WHEEL
pyworldquant-0.0.2.dist-info/top_level.txt
pyworldquant-0.0.2.dist-info/RECORD
