Metadata-Version: 2.1
Name: pyworldquant
Version: 0.0.2
Summary: A python tool developed for WorldQuant Brain Platform User
Author-email: Jeremy Meng <jeremytousnet@gmail.com>
License: Mozilla Public License Version 2.0
Project-URL: repository, https://github.com/whosquant/pyworldquant
Classifier: Development Status :: 1 - Planning
Classifier: Intended Audience :: Education
Classifier: License :: OSI Approved :: Mozilla Public License 2.0 (MPL 2.0)
Classifier: Programming Language :: Python :: 3
Classifier: Programming Language :: Python :: 3.6
Classifier: Programming Language :: Python :: 3.7
Classifier: Programming Language :: Python :: 3.8
Requires-Python: >=3.6
License-File: LICENSE
Requires-Dist: requests
Requires-Dist: toml
Requires-Dist: pandas
Provides-Extra: dev
Requires-Dist: autopep8 ; extra == 'dev'
Requires-Dist: isort ; extra == 'dev'
Requires-Dist: pre-commit ; extra == 'dev'
Requires-Dist: setuptools ; extra == 'dev'
Requires-Dist: twine ; extra == 'dev'
Requires-Dist: upgrade-ensurepip ; extra == 'dev'
Requires-Dist: wheel ; extra == 'dev'
Provides-Extra: test
Requires-Dist: mypy ; extra == 'test'
Requires-Dist: pydantic ; extra == 'test'
Requires-Dist: pylint ; extra == 'test'
Requires-Dist: pytest ; extra == 'test'
Requires-Dist: pytest-cov ; extra == 'test'
